robotraconteur_camera_driver.py
robotraconteur_camera_driver-0.2.0.dist-info/LICENSE.txt
robotraconteur_camera_driver-0.2.0.dist-info/METADATA
robotraconteur_camera_driver-0.2.0.dist-info/WHEEL
robotraconteur_camera_driver-0.2.0.dist-info/entry_points.txt
robotraconteur_camera_driver-0.2.0.dist-info/top_level.txt
robotraconteur_camera_driver-0.2.0.dist-info/RECORD
