Metadata-Version: 2.1
Name: robotraconteur-camera-driver
Version: 0.2.0
Summary: Robot Raconteur camera driver using OpenCV camera capture
Author-email: John Wason <wason@wasontech.com>
License: Apache-2.0
Requires-Python: >=3.8
License-File: LICENSE.txt
Requires-Dist: robotraconteur
Requires-Dist: robotraconteurcompanion
Requires-Dist: drekar-launch-process
Requires-Dist: opencv-contrib-python
Provides-Extra: test
Requires-Dist: pytest; extra == "test"
